ids_peak_afl/__init__.py
ids_peak_afl/_ids_peak_afl_python_interface.so
ids_peak_afl/exceptions.py
ids_peak_afl/ids_peak_afl.py
ids_peak_afl/libids_peak_afl.so
ids_peak_afl/pipeline/__init__.py
ids_peak_afl/pipeline/_internal/__init__.py
ids_peak_afl/pipeline/_internal/utils.py
ids_peak_afl/pipeline/datatypes/__init__.py
ids_peak_afl/pipeline/datatypes/datatypes.py
ids_peak_afl/pipeline/features/__init__.py
ids_peak_afl/pipeline/features/auto_percentile.py
ids_peak_afl/pipeline/features/auto_target.py
ids_peak_afl/pipeline/features/auto_tolerance.py
ids_peak_afl/pipeline/features/brightness_algorithm.py
ids_peak_afl/pipeline/features/brightness_component.py
ids_peak_afl/pipeline/features/brightness_limit.py
ids_peak_afl/pipeline/features/focus_limit.py
ids_peak_afl/pipeline/features/hysteresis.py
ids_peak_afl/pipeline/features/ifeature.py
ids_peak_afl/pipeline/features/roi.py
ids_peak_afl/pipeline/features/search_algorithm.py
ids_peak_afl/pipeline/features/sharpness_algorithm.py
ids_peak_afl/pipeline/features/skip_frames.py
ids_peak_afl/pipeline/features/weighted_rois.py
ids_peak_afl/pipeline/modules/__init__.py
ids_peak_afl/pipeline/modules/basic_auto_features.py
ids_peak_afl/pipeline/modules/_internal/__init__.py
ids_peak_afl/pipeline/modules/_internal/generic_auto_features.py
ids_peak_afl/pipeline/modules/controllers/__init__.py
ids_peak_afl/pipeline/modules/controllers/basic_auto_brightness.py
ids_peak_afl/pipeline/modules/controllers/basic_auto_focus.py
ids_peak_afl/pipeline/modules/controllers/basic_auto_white_balance.py
ids_peak_afl/pipeline/modules/controllers/controller_datatypes.py
ids_peak_afl/pipeline/modules/controllers/_internal/__init__.py
ids_peak_afl/pipeline/modules/controllers/_internal/callback_manager.py
ids_peak_afl/pipeline/modules/controllers/_internal/generic_auto_brightness.py
ids_peak_afl/pipeline/modules/controllers/_internal/generic_auto_focus.py
ids_peak_afl-2.0.0.0.3.dist-info/METADATA
ids_peak_afl-2.0.0.0.3.dist-info/WHEEL
ids_peak_afl-2.0.0.0.3.dist-info/top_level.txt
ids_peak_afl-2.0.0.0.3.dist-info/RECORD
ids_peak_afl-2.0.0.0.3.dist-info/licenses/LICENSE
ids_peak_afl-2.0.0.0.3.dist-info/licenses/third_party_copyrights.txt
ids_peak_afl-2.0.0.0.3.dist-info/licenses/third_party_licenses.txt
